live_server/__init__.py
live_server/cli.py
live_server/global_vars.py
live_server/inject.py
live_server/liveServer.js
live_server/server.py
live_server/watcher.py
live_server-0.9.9.dist-info/LICENSE
live_server-0.9.9.dist-info/METADATA
live_server-0.9.9.dist-info/WHEEL
live_server-0.9.9.dist-info/entry_points.txt
live_server-0.9.9.dist-info/top_level.txt
live_server-0.9.9.dist-info/RECORD
