Metadata-Version: 2.1
Name: live-server
Version: 0.9.9
Summary: Serves your pages for development and automatically reloads when changed.
Home-page: https://github.com/ajitid/live_server
Author: Ajit Singh
Author-email: ajit.singh2905@gmail.com
License: UNKNOWN
Platform: UNKNOWN
Classifier: Development Status :: 5 - Production/Stable
Classifier: Environment :: Web Environment
Classifier: Intended Audience :: Developers
Classifier: Programming Language :: Python :: 3
Classifier: License :: OSI Approved :: MIT License
Classifier: Operating System :: OS Independent
Requires-Python: >=3.4
